micromamba_install_locked_pip_dependencies/__init__.py
micromamba_install_locked_pip_dependencies/cli.py
micromamba_install_locked_pip_dependencies-1.0.2.dist-info/METADATA
micromamba_install_locked_pip_dependencies-1.0.2.dist-info/WHEEL
micromamba_install_locked_pip_dependencies-1.0.2.dist-info/entry_points.txt
micromamba_install_locked_pip_dependencies-1.0.2.dist-info/licenses/LICENSE.txt
micromamba_install_locked_pip_dependencies-1.0.2.dist-info/RECORD
