Metadata-Version: 2.1
Name: micromamba-install-locked-pip-dependencies
Version: 1.0.2
Summary: Install pip dependencies from new-style lockfiles
Project-URL: Documentation, https://github.com/maresb/micromamba-install-locked-pip-dependencies#readme
Project-URL: Issues, https://github.com/maresb/micromamba-install-locked-pip-dependencies/issues
Project-URL: Source, https://github.com/maresb/micromamba-install-locked-pip-dependencies
Author-email: Ben Mares <services-micromamba-install-locked-pip-dependencies@tensorial.com>
License-File: LICENSE.txt
Classifier: Programming Language :: Python
Classifier: Programming Language :: Python :: 3.6
Classifier: Programming Language :: Python :: 3.7
Classifier: Programming Language :: Python :: 3.8
Classifier: Programming Language :: Python :: 3.9
Classifier: Programming Language :: Python :: 3.10
Classifier: Programming Language :: Python :: 3.11
Classifier: Programming Language :: Python :: Implementation :: CPython
Classifier: Programming Language :: Python :: Implementation :: PyPy
Requires-Python: >=3.6
